systemair_api/__init__.py
systemair_api/__main__.py
systemair_api/__version__.py
systemair_api/api/__init__.py
systemair_api/api/systemair_api.py
systemair_api/api/websocket_client.py
systemair_api/auth/__init__.py
systemair_api/auth/authenticator.py
systemair_api/models/__init__.py
systemair_api/models/ventilation_data.py
systemair_api/models/ventilation_unit.py
systemair_api/utils/__init__.py
systemair_api/utils/constants.py
systemair_api/utils/exceptions.py
systemair_api/utils/register_constants.py
systemair_api_promises-0.1.1.dist-info/licenses/LICENSE
systemair_api_promises-0.1.1.dist-info/METADATA
systemair_api_promises-0.1.1.dist-info/WHEEL
systemair_api_promises-0.1.1.dist-info/entry_points.txt
systemair_api_promises-0.1.1.dist-info/top_level.txt
systemair_api_promises-0.1.1.dist-info/RECORD
