Metadata-Version: 2.4
Name: systemair-api-promises
Version: 0.1.1
Summary: Python library for communicating with and controlling Systemair ventilation units
Home-page: https://github.com/Promises/SystemAIR-API
Author: Henning Berge
Author-email: Henning Berge <henning.ber@gmail.com>
Maintainer-email: Henning Berge <henning.ber@gmail.com>
License: MIT
Project-URL: Homepage, https://github.com/promises/SystemAIR-API
Project-URL: Documentation, https://github.com/promises/SystemAIR-API#readme
Project-URL: Repository, https://github.com/promises/SystemAIR-API
Project-URL: Bug Tracker, https://github.com/promises/SystemAIR-API/issues
Project-URL: Changelog, https://github.com/promises/SystemAIR-API/blob/main/CHANGELOG.md
Keywords: systemair,ventilation,hvac,home-automation,api
Classifier: Development Status :: 3 - Alpha
Classifier: Intended Audience :: Developers
Classifier: License :: OSI Approved :: MIT License
Classifier: Programming Language :: Python :: 3
Classifier: Programming Language :: Python :: 3.7
Classifier: Programming Language :: Python :: 3.8
Classifier: Programming Language :: Python :: 3.9
Classifier: Programming Language :: Python :: 3.10
Classifier: Programming Language :: Python :: 3.11
Classifier: Topic :: Home Automation
Classifier: Topic :: Software Development :: Libraries :: Python Modules
Classifier: Operating System :: OS Independent
Requires-Python: >=3.7
License-File: LICENSE
Requires-Dist: requests>=2.28.0
Requires-Dist: websocket-client>=1.3.1
Requires-Dist: beautifulsoup4>=4.10.0
Requires-Dist: python-dotenv>=0.19.0
Provides-Extra: dev
Requires-Dist: pytest>=6.0; extra == "dev"
Requires-Dist: pytest-cov>=3.0; extra == "dev"
Requires-Dist: pytest-mock>=3.6; extra == "dev"
Requires-Dist: requests-mock>=1.9; extra == "dev"
Requires-Dist: black>=22.0; extra == "dev"
Requires-Dist: isort>=5.10; extra == "dev"
Requires-Dist: flake8>=4.0; extra == "dev"
Requires-Dist: mypy>=0.950; extra == "dev"
Requires-Dist: sphinx>=4.0; extra == "dev"
Requires-Dist: sphinx-rtd-theme>=1.0; extra == "dev"
Requires-Dist: sphinx-autodoc-typehints>=1.12; extra == "dev"
Requires-Dist: pre-commit>=2.15; extra == "dev"
Requires-Dist: build>=0.8; extra == "dev"
Requires-Dist: twine>=4.0; extra == "dev"
Dynamic: author
Dynamic: home-page
Dynamic: license-file
Dynamic: requires-python
